yaw_cli/__init__.py
yaw_cli/commandline/__init__.py
yaw_cli/commandline/main.py
yaw_cli/commandline/subcommands.py
yaw_cli/commandline/utils.py
yaw_cli/pipeline/__init__.py
yaw_cli/pipeline/data.py
yaw_cli/pipeline/default_setup.py
yaw_cli/pipeline/directories.py
yaw_cli/pipeline/logger.py
yaw_cli/pipeline/merge.py
yaw_cli/pipeline/plot.py
yaw_cli/pipeline/processing.py
yaw_cli/pipeline/project.py
yaw_cli/pipeline/tasks.py
yet_another_wizz_cli-1.3.0.dist-info/LICENSE
yet_another_wizz_cli-1.3.0.dist-info/METADATA
yet_another_wizz_cli-1.3.0.dist-info/WHEEL
yet_another_wizz_cli-1.3.0.dist-info/entry_points.txt
yet_another_wizz_cli-1.3.0.dist-info/top_level.txt
yet_another_wizz_cli-1.3.0.dist-info/RECORD
