Metadata-Version: 2.2
Name: yet_another_wizz_cli
Version: 1.3.0
Summary: Command line client for yet_another_wizz.
Home-page: https://github.com/jlvdb/yet_another_wizz_cli.git
Author-email: Jan Luca van den Busch <jlvdb@astro.ruhr-uni-bochum.de>
License: GPL-3.0-or-later
Classifier: Intended Audience :: Science/Research
Classifier: Topic :: Scientific/Engineering :: Astronomy
Classifier: Programming Language :: Python :: 3
Classifier: License :: OSI Approved :: GNU General Public License v3 or later (GPLv3+)
Requires-Python: >=3.8
License-File: LICENSE
Requires-Dist: numpy
Requires-Dist: pandas
Requires-Dist: pyyaml
Requires-Dist: matplotlib
Requires-Dist: yet-another-wizz<3.0,>=2.5.5
Provides-Extra: plot
Requires-Dist: matplotlib; extra == "plot"
Provides-Extra: style
Requires-Dist: black; extra == "style"
Requires-Dist: isort; extra == "style"
Requires-Dist: flake8; extra == "style"
Requires-Dist: pre-commit; extra == "style"
Provides-Extra: test
Requires-Dist: coverage; extra == "test"
Requires-Dist: pytest; extra == "test"
Requires-Dist: pytest-cov; extra == "test"
Provides-Extra: dev
Requires-Dist: yet_another_wizz_cli[style]; extra == "dev"
Requires-Dist: yet_another_wizz_cli[test]; extra == "dev"
Requires-Dist: ipykernel; extra == "dev"
Dynamic: home-page
